LICENSE
MANIFEST.in
README.md
setup.py
easyemail/__init__.py
easyemail/base.py
easyemail.egg-info/PKG-INFO
easyemail.egg-info/SOURCES.txt
easyemail.egg-info/dependency_links.txt
easyemail.egg-info/not-zip-safe
easyemail.egg-info/top_level.txt