Metadata-Version: 1.1
Name: easyemail
Version: 0.3.0
Summary: Simple lib abstracting email sending with smtplib.
Home-page: http://github.com/niktto/easyemail/
Author: Marek Szwalkiewicz
Author-email: marek@szwalkiewicz.waw.pl
License: Copyright (c) 2013, Marek Szwałkiewicz
